<?xml version="1.0" encoding="utf-8"?><annotation>
  <folder>JPEGImages</folder>
  <filename>light_04_short_04_1_256</filename>
  <path>F:\PCB\PCB_DATASET_New\VOCPCB_800\_crop_600\JPEGImages\light_04_short_04_1_256.jpg</path>
  <size>
    <width>600</width>
    <height>600</height>
    <depth>3</depth>
  </size>
  <segmented>0</segmented>
  <object>
    <name>short</name>
    <pose>Unspecified</pose>
    <truncated>0</truncated>
    <difficult>0</difficult>
    <bndbox>
      <xmin>287</xmin>
      <ymin>341</ymin>
      <xmax>335</xmax>
      <ymax>380</ymax>
    </bndbox>
  </object>
  <object>
    <name>short</name>
    <pose>Unspecified</pose>
    <truncated>0</truncated>
    <difficult>0</difficult>
    <bndbox>
      <xmin>99</xmin>
      <ymin>458</ymin>
      <xmax>135</xmax>
      <ymax>491</ymax>
    </bndbox>
  </object>
</annotation>