<?xml version="1.0" encoding="utf-8"?><annotation>
  <folder>JPEGImages</folder>
  <filename>light_08_spur_10_5_256</filename>
  <path>F:\PCB\PCB_DATASET_New\VOCPCB_800\_crop_600\JPEGImages\light_08_spur_10_5_256.jpg</path>
  <size>
    <width>600</width>
    <height>600</height>
    <depth>3</depth>
  </size>
  <segmented>0</segmented>
  <object>
    <name>spur</name>
    <pose>Unspecified</pose>
    <truncated>0</truncated>
    <difficult>0</difficult>
    <bndbox>
      <xmin>386</xmin>
      <ymin>342</ymin>
      <xmax>406</xmax>
      <ymax>383</ymax>
    </bndbox>
  </object>
  <object>
    <name>spur</name>
    <pose>Unspecified</pose>
    <truncated>0</truncated>
    <difficult>0</difficult>
    <bndbox>
      <xmin>441</xmin>
      <ymin>223</ymin>
      <xmax>458</xmax>
      <ymax>258</ymax>
    </bndbox>
  </object>
  <object>
    <name>spur</name>
    <pose>Unspecified</pose>
    <truncated>0</truncated>
    <difficult>0</difficult>
    <bndbox>
      <xmin>1</xmin>
      <ymin>377</ymin>
      <xmax>25</xmax>
      <ymax>396</ymax>
    </bndbox>
  </object>
</annotation>